cmsketch/base.py
cmsketch/_core.pyi
cmsketch/__init__.py
cmsketch/_version.py
cmsketch/_core.cpython-311-x86_64-linux-gnu.so
cmsketch/py.typed
cmsketch/py/count_min_sketch.py
cmsketch/py/hash_util.py
cmsketch-0.1.11.dist-info/METADATA
cmsketch-0.1.11.dist-info/WHEEL
cmsketch-0.1.11.dist-info/RECORD
cmsketch-0.1.11.dist-info/licenses/LICENSE
