Metadata-Version: 2.2
Name: cmsketch
Version: 0.1.11
Summary: High-performance Count-Min Sketch implementation with C++ and Python versions
Keywords: count-min-sketch,probabilistic,data-structure,streaming
Author-Email: isaac-fei <isaac.omega.fei@gmail.com>
Maintainer-Email: isaac-fei <isaac.omega.fei@gmail.com>
License: MIT License
Classifier: Development Status :: 4 - Beta
Classifier: Intended Audience :: Developers
Classifier: License :: OSI Approved :: MIT License
Classifier: Programming Language :: Python :: 3
Classifier: Programming Language :: Python :: 3.11
Classifier: Programming Language :: Python :: 3.12
Classifier: Programming Language :: C++
Classifier: Topic :: Scientific/Engineering
Classifier: Topic :: Software Development :: Libraries :: Python Modules
Classifier: Operating System :: OS Independent
Project-URL: Homepage, https://github.com/isaac-fate/count-min-sketch
Project-URL: Repository, https://github.com/isaac-fate/count-min-sketch
Project-URL: Documentation, https://github.com/isaac-fate/count-min-sketch#readme
Project-URL: Issues, https://github.com/isaac-fate/count-min-sketch/issues
Requires-Python: >=3.11
Provides-Extra: dev
Requires-Dist: pytest>=8.0.0; extra == "dev"
Requires-Dist: pytest-benchmark>=4.0.0; extra == "dev"
Requires-Dist: build>=1.0.0; extra == "dev"
